MANIFEST.in
README.rst
setup.py
django_jqchat.egg-info/PKG-INFO
django_jqchat.egg-info/SOURCES.txt
django_jqchat.egg-info/dependency_links.txt
django_jqchat.egg-info/not-zip-safe
django_jqchat.egg-info/requires.txt
django_jqchat.egg-info/top_level.txt
docs/index.rst
jqchat/__init__.py
jqchat/admin.py
jqchat/models.py
jqchat/tests.py
jqchat/urls.py
jqchat/views.py
jqchat/fixtures/test_jqchat.json
jqchat/migrations/0001_initial.py
jqchat/migrations/0002_auto__chg_field_room_name.py
jqchat/migrations/__init__.py
jqchat/static/jqchat/jqchat.js
jqchat/templates/admin/jqchat/room/change_form.html
jqchat/templates/jqchat/_chat_form.html
jqchat/templates/jqchat/base.html
jqchat/templates/jqchat/chat_payload.json
jqchat/templates/jqchat/chat_test.html
jqchat/templates/jqchat/chat_test_with_desc.html