Metadata-Version: 1.1
Name: django-jqchat
Version: 0.2
Summary: An extensible instant messenger thingy for Django
Home-page: https://github.com/tomscytale/django-jqchat
Author: Richard Barran
Author-email: richardb...@gmail.com
License: UNKNOWN
Platform: UNKNOWN
Classifier: Framework :: Django
Classifier: Intended Audience :: Developers
Classifier: Intended Audience :: System Administrators
Classifier: Operating System :: OS Independent
Classifier: Topic :: Software Development
